{
  "ts": "2026-02-12T15:15:29.874861+00:00",
  "method": "GET",
  "path": "/clinic/care-requests",
  "status": 200,
  "request": null,
  "params": null,
  "response": [
    {
      "id": "d6903509-65a7-4975-98bf-e3f8dc6c39e0",
      "pet_id": "37a4bc4e-ff58-4f04-bb90-ddf836786dfd",
      "title": "Clinic triage clinic-alpha-20260212T151504Z",
      "description": "Intermittent cough and lower appetite",
      "location": "Amman",
      "priority": "medium",
      "status": "in_progress",
      "requested_by": "97052c92-910f-4061-976f-c8a991cdaaf4",
      "requested_by_name": "Demo Clinic",
      "assigned_vet_id": "1382dcc7-3cd5-4be2-b4e9-8bad76a7d864",
      "assigned_clinic_id": "97052c92-910f-4061-976f-c8a991cdaaf4",
      "attachments": [],
      "follow_up_context": null,
      "follow_up_due_date": null,
      "reminder_enabled": false,
      "created_at": "2026-02-12T15:15:04.685000",
      "updated_at": "2026-02-12T15:15:04.739000",
      "clinic_notes": "clinic-handoff-complete-clinic-alpha-20260212T151504Z"
    },
    {
      "id": "741a3e54-d025-4e15-97f8-cc86ea358c1d",
      "pet_id": "acbbb5f0-3269-4781-83bf-da505723a97e",
      "title": "Clinic care #3 beta-clinic-cycle-20260212T151455Z",
      "description": "Symptoms: Reduced appetite (beta-clinic-cycle-20260212T151455Z)",
      "location": "Amman",
      "priority": "urgent",
      "status": "completed",
      "requested_by": "1c510527-ab2b-459c-be79-36a0f65850ec",
      "requested_by_name": "Beta Clinic User",
      "assigned_vet_id": "1382dcc7-3cd5-4be2-b4e9-8bad76a7d864",
      "assigned_clinic_id": null,
      "attachments": [],
      "follow_up_context": null,
      "follow_up_due_date": null,
      "reminder_enabled": false,
      "created_at": "2026-02-12T15:14:58.359000",
      "updated_at": "2026-02-12T15:14:58.433000",
      "diagnosis": "Dx-3-beta-clinic-cycle-20260212T151455Z",
      "prescription": "Rx-3-beta-clinic-cycle-20260212T151455Z",
      "vet_notes": "Follow-up in 4 days (beta-clinic-cycle-20260212T151455Z)"
    },
    {
      "id": "9547ee2a-2743-4545-9317-9bc5dc924929",
      "pet_id": "2f259d1b-d314-4a49-839b-b49c14a7d26c",
      "title": "Clinic care #2 beta-clinic-cycle-20260212T151455Z",
      "description": "Symptoms: Mild cough (beta-clinic-cycle-20260212T151455Z)",
      "location": "Amman",
      "priority": "normal",
      "status": "completed",
      "requested_by": "1c510527-ab2b-459c-be79-36a0f65850ec",
      "requested_by_name": "Beta Clinic User",
      "assigned_vet_id": "1382dcc7-3cd5-4be2-b4e9-8bad76a7d864",
      "assigned_clinic_id": null,
      "attachments": [],
      "follow_up_context": null,
      "follow_up_due_date": null,
      "reminder_enabled": false,
      "created_at": "2026-02-12T15:14:58.348000",
      "updated_at": "2026-02-12T15:14:58.409000",
      "diagnosis": "Dx-2-beta-clinic-cycle-20260212T151455Z",
      "prescription": "Rx-2-beta-clinic-cycle-20260212T151455Z",
      "vet_notes": "Follow-up in 3 days (beta-clinic-cycle-20260212T151455Z)"
    },
    {
      "id": "518f2db3-620a-4b5f-b1a0-0fb38ff6a111",
      "pet_id": "737a4811-234a-477c-80f9-ef07cfca0057",
      "title": "Clinic care #1 beta-clinic-cycle-20260212T151455Z",
      "description": "Symptoms: Vomiting + lethargy (beta-clinic-cycle-20260212T151455Z)",
      "location": "Amman",
      "priority": "high",
      "status": "completed",
      "requested_by": "1c510527-ab2b-459c-be79-36a0f65850ec",
      "requested_by_name": "Beta Clinic User",
      "assigned_vet_id": "1382dcc7-3cd5-4be2-b4e9-8bad76a7d864",
      "assigned_clinic_id": null,
      "attachments": [],
      "follow_up_context": null,
      "follow_up_due_date": null,
      "reminder_enabled": false,
      "created_at": "2026-02-12T15:14:58.340000",
      "updated_at": "2026-02-12T15:14:58.382000",
      "diagnosis": "Dx-1-beta-clinic-cycle-20260212T151455Z",
      "prescription": "Rx-1-beta-clinic-cycle-20260212T151455Z",
      "vet_notes": "Follow-up in 2 days (beta-clinic-cycle-20260212T151455Z)"
    },
    {
      "id": "5246c3e1-fd09-4afb-8cf1-640a217c96d2",
      "pet_id": "f79566c1-1ff1-4bff-926f-9e857ad333c1",
      "title": "Clinic care #3 beta-clinic-cycle-20260212T151400Z",
      "description": "Symptoms: Reduced appetite (beta-clinic-cycle-20260212T151400Z)",
      "location": "Amman",
      "priority": "urgent",
      "status": "pending",
      "requested_by": "51857c30-1079-4e36-b925-c911bb7c0f71",
      "requested_by_name": "Beta Clinic User",
      "assigned_vet_id": null,
      "assigned_clinic_id": null,
      "attachments": [],
      "follow_up_context": null,
      "follow_up_due_date": null,
      "reminder_enabled": false,
      "created_at": "2026-02-12T15:14:04.650000",
      "updated_at": "2026-02-12T15:14:04.650000"
    },
    {
      "id": "9ff24f70-67b8-4bb9-8e66-c4488a0c997c",
      "pet_id": "41e4f263-952b-4310-a937-2729543d7ff5",
      "title": "Clinic care #2 beta-clinic-cycle-20260212T151400Z",
      "description": "Symptoms: Mild cough (beta-clinic-cycle-20260212T151400Z)",
      "location": "Amman",
      "priority": "normal",
      "status": "pending",
      "requested_by": "51857c30-1079-4e36-b925-c911bb7c0f71",
      "requested_by_name": "Beta Clinic User",
      "assigned_vet_id": null,
      "assigned_clinic_id": null,
      "attachments": [],
      "follow_up_context": null,
      "follow_up_due_date": null,
      "reminder_enabled": false,
      "created_at": "2026-02-12T15:14:04.641000",
      "updated_at": "2026-02-12T15:14:04.641000"
    },
    {
      "id": "2dcebc05-bb93-4156-b876-f1bbfcce91bd",
      "pet_id": "7665e4a4-434a-43d5-a18a-c1a0c9563455",
      "title": "Clinic care #1 beta-clinic-cycle-20260212T151400Z",
      "description": "Symptoms: Vomiting + lethargy (beta-clinic-cycle-20260212T151400Z)",
      "location": "Amman",
      "priority": "high",
      "status": "pending",
      "requested_by": "51857c30-1079-4e36-b925-c911bb7c0f71",
      "requested_by_name": "Beta Clinic User",
      "assigned_vet_id": null,
      "assigned_clinic_id": null,
      "attachments": [],
      "follow_up_context": null,
      "follow_up_due_date": null,
      "reminder_enabled": false,
      "created_at": "2026-02-12T15:14:04.627000",
      "updated_at": "2026-02-12T15:14:04.627000"
    },
    {
      "id": "63a3a3e5-b74a-4dc0-809a-6e418e621358",
      "pet_id": "1918dd1c-6b34-4037-9698-07fc1eb23477",
      "title": "Attachment Continuity attach-fix-20260212T130147Z #11",
      "description": "Loop 11",
      "location": "Amman",
      "priority": "high",
      "status": "completed",
      "requested_by": "199cd06e-0ac0-4ddc-beaa-2392c4195880",
      "requested_by_name": "Attach Fix User",
      "assigned_vet_id": "1382dcc7-3cd5-4be2-b4e9-8bad76a7d864",
      "assigned_clinic_id": null,
      "attachments": [
        "inline://attach-fix-20260212T130147Z-11-a",
        "inline://attach-fix-20260212T130147Z-11-b"
      ],
      "follow_up_context": "Loop-11",
      "follow_up_due_date": null,
      "reminder_enabled": false,
      "created_at": "2026-02-12T13:01:49.898000",
      "updated_at": "2026-02-12T13:01:49.925000",
      "diagnosis": "Dx-11",
      "prescription": "Rx-11",
      "vet_notes": null
    },
    {
      "id": "acc03be8-e83d-4805-a5e7-cac65e9d97ca",
      "pet_id": "1918dd1c-6b34-4037-9698-07fc1eb23477",
      "title": "Attachment Continuity attach-fix-20260212T130147Z #10",
      "description": "Loop 10",
      "location": "Amman",
      "priority": "high",
      "status": "completed",
      "requested_by": "199cd06e-0ac0-4ddc-beaa-2392c4195880",
      "requested_by_name": "Attach Fix User",
      "assigned_vet_id": "1382dcc7-3cd5-4be2-b4e9-8bad76a7d864",
      "assigned_clinic_id": null,
      "attachments": [
        "inline://attach-fix-20260212T130147Z-10-a",
        "inline://attach-fix-20260212T130147Z-10-b"
      ],
      "follow_up_context": "Loop-10",
      "follow_up_due_date": null,
      "reminder_enabled": false,
      "created_at": "2026-02-12T13:01:49.869000",
      "updated_at": "2026-02-12T13:01:49.887000",
      "diagnosis": "Dx-10",
      "prescription": "Rx-10",
      "vet_notes": null
    },
    {
      "id": "0f0af582-d29c-4f37-a4ff-e8da4f41df53",
      "pet_id": "1918dd1c-6b34-4037-9698-07fc1eb23477",
      "title": "Attachment Continuity attach-fix-20260212T130147Z #9",
      "description": "Loop 9",
      "location": "Amman",
      "priority": "high",
      "status": "completed",
      "requested_by": "199cd06e-0ac0-4ddc-beaa-2392c4195880",
      "requested_by_name": "Attach Fix User",
      "assigned_vet_id": "1382dcc7-3cd5-4be2-b4e9-8bad76a7d864",
      "assigned_clinic_id": null,
      "attachments": [
        "inline://attach-fix-20260212T130147Z-9-a",
        "inline://attach-fix-20260212T130147Z-9-b"
      ],
      "follow_up_context": "Loop-9",
      "follow_up_due_date": null,
      "reminder_enabled": false,
      "created_at": "2026-02-12T13:01:49.837000",
      "updated_at": "2026-02-12T13:01:49.859000",
      "diagnosis": "Dx-9",
      "prescription": "Rx-9",
      "vet_notes": null
    },
    {
      "id": "fe555b6a-de37-498f-a351-6ca28c38c955",
      "pet_id": "1918dd1c-6b34-4037-9698-07fc1eb23477",
      "title": "Attachment Continuity attach-fix-20260212T130147Z #8",
      "description": "Loop 8",
      "location": "Amman",
      "priority": "high",
      "status": "completed",
      "requested_by": "199cd06e-0ac0-4ddc-beaa-2392c4195880",
      "requested_by_name": "Attach Fix User",
      "assigned_vet_id": "1382dcc7-3cd5-4be2-b4e9-8bad76a7d864",
      "assigned_clinic_id": null,
      "attachments": [
        "inline://attach-fix-20260212T130147Z-8-a",
        "inline://attach-fix-20260212T130147Z-8-b"
      ],
      "follow_up_context": "Loop-8",
      "follow_up_due_date": null,
      "reminder_enabled": false,
      "created_at": "2026-02-12T13:01:49.809000",
      "updated_at": "2026-02-12T13:01:49.828000",
      "diagnosis": "Dx-8",
      "prescription": "Rx-8",
      "vet_notes": null
    },
    {
      "id": "6a6d3327-4de0-4e9d-8b6b-0de04a8ed519",
      "pet_id": "1918dd1c-6b34-4037-9698-07fc1eb23477",
      "title": "Attachment Continuity attach-fix-20260212T130147Z #7",
      "description": "Loop 7",
      "location": "Amman",
      "priority": "high",
      "status": "completed",
      "requested_by": "199cd06e-0ac0-4ddc-beaa-2392c4195880",
      "requested_by_name": "Attach Fix User",
      "assigned_vet_id": "1382dcc7-3cd5-4be2-b4e9-8bad76a7d864",
      "assigned_clinic_id": null,
      "attachments": [
        "inline://attach-fix-20260212T130147Z-7-a",
        "inline://attach-fix-20260212T130147Z-7-b"
      ],
      "follow_up_context": "Loop-7",
      "follow_up_due_date": null,
      "reminder_enabled": false,
      "created_at": "2026-02-12T13:01:49.779000",
      "updated_at": "2026-02-12T13:01:49.799000",
      "diagnosis": "Dx-7",
      "prescription": "Rx-7",
      "vet_notes": null
    },
    {
      "id": "796111c7-b4a3-45ed-a1ab-683f1811c902",
      "pet_id": "1918dd1c-6b34-4037-9698-07fc1eb23477",
      "title": "Attachment Continuity attach-fix-20260212T130147Z #6",
      "description": "Loop 6",
      "location": "Amman",
      "priority": "high",
      "status": "completed",
      "requested_by": "199cd06e-0ac0-4ddc-beaa-2392c4195880",
      "requested_by_name": "Attach Fix User",
      "assigned_vet_id": "1382dcc7-3cd5-4be2-b4e9-8bad76a7d864",
      "assigned_clinic_id": null,
      "attachments": [
        "inline://attach-fix-20260212T130147Z-6-a",
        "inline://attach-fix-20260212T130147Z-6-b"
      ],
      "follow_up_context": "Loop-6",
      "follow_up_due_date": null,
      "reminder_enabled": false,
      "created_at": "2026-02-12T13:01:49.749000",
      "updated_at": "2026-02-12T13:01:49.768000",
      "diagnosis": "Dx-6",
      "prescription": "Rx-6",
      "vet_notes": null
    },
    {
      "id": "1712b58d-cbc3-43c3-9999-74631e9a6e48",
      "pet_id": "1918dd1c-6b34-4037-9698-07fc1eb23477",
      "title": "Attachment Continuity attach-fix-20260212T130147Z #5",
      "description": "Loop 5",
      "location": "Amman",
      "priority": "high",
      "status": "completed",
      "requested_by": "199cd06e-0ac0-4ddc-beaa-2392c4195880",
      "requested_by_name": "Attach Fix User",
      "assigned_vet_id": "1382dcc7-3cd5-4be2-b4e9-8bad76a7d864",
      "assigned_clinic_id": null,
      "attachments": [
        "inline://attach-fix-20260212T130147Z-5-a",
        "inline://attach-fix-20260212T130147Z-5-b"
      ],
      "follow_up_context": "Loop-5",
      "follow_up_due_date": null,
      "reminder_enabled": false,
      "created_at": "2026-02-12T13:01:49.722000",
      "updated_at": "2026-02-12T13:01:49.740000",
      "diagnosis": "Dx-5",
      "prescription": "Rx-5",
      "vet_notes": null
    },
    {
      "id": "d5ed639b-3d87-4523-a018-7a1e4b3df13c",
      "pet_id": "1918dd1c-6b34-4037-9698-07fc1eb23477",
      "title": "Attachment Continuity attach-fix-20260212T130147Z #4",
      "description": "Loop 4",
      "location": "Amman",
      "priority": "high",
      "status": "completed",
      "requested_by": "199cd06e-0ac0-4ddc-beaa-2392c4195880",
      "requested_by_name": "Attach Fix User",
      "assigned_vet_id": "1382dcc7-3cd5-4be2-b4e9-8bad76a7d864",
      "assigned_clinic_id": null,
      "attachments": [
        "inline://attach-fix-20260212T130147Z-4-a",
        "inline://attach-fix-20260212T130147Z-4-b"
      ],
      "follow_up_context": "Loop-4",
      "follow_up_due_date": null,
      "reminder_enabled": false,
      "created_at": "2026-02-12T13:01:49.692000",
      "updated_at": "2026-02-12T13:01:49.713000",
      "diagnosis": "Dx-4",
      "prescription": "Rx-4",
      "vet_notes": null
    },
    {
      "id": "961ca18d-bf15-40bd-9c53-46d9026ac1ae",
      "pet_id": "1918dd1c-6b34-4037-9698-07fc1eb23477",
      "title": "Attachment Continuity attach-fix-20260212T130147Z #3",
      "description": "Loop 3",
      "location": "Amman",
      "priority": "high",
      "status": "completed",
      "requested_by": "199cd06e-0ac0-4ddc-beaa-2392c4195880",
      "requested_by_name": "Attach Fix User",
      "assigned_vet_id": "1382dcc7-3cd5-4be2-b4e9-8bad76a7d864",
      "assigned_clinic_id": null,
      "attachments": [
        "inline://attach-fix-20260212T130147Z-3-a",
        "inline://attach-fix-20260212T130147Z-3-b"
      ],
      "follow_up_context": "Loop-3",
      "follow_up_due_date": null,
      "reminder_enabled": false,
      "created_at": "2026-02-12T13:01:49.663000",
      "updated_at": "2026-02-12T13:01:49.683000",
      "diagnosis": "Dx-3",
      "prescription": "Rx-3",
      "vet_notes": null
    },
    {
      "id": "1e815e6f-5e68-4d80-9abe-47a93d9c42f5",
      "pet_id": "1918dd1c-6b34-4037-9698-07fc1eb23477",
      "title": "Attachment Continuity attach-fix-20260212T130147Z #2",
      "description": "Loop 2",
      "location": "Amman",
      "priority": "high",
      "status": "completed",
      "requested_by": "199cd06e-0ac0-4ddc-beaa-2392c4195880",
      "requested_by_name": "Attach Fix User",
      "assigned_vet_id": "1382dcc7-3cd5-4be2-b4e9-8bad76a7d864",
      "assigned_clinic_id": null,
      "attachments": [
        "inline://attach-fix-20260212T130147Z-2-a",
        "inline://attach-fix-20260212T130147Z-2-b"
      ],
      "follow_up_context": "Loop-2",
      "follow_up_due_date": null,
      "reminder_enabled": false,
      "created_at": "2026-02-12T13:01:49.627000",
      "updated_at": "2026-02-12T13:01:49.652000",
      "diagnosis": "Dx-2",
      "prescription": "Rx-2",
      "vet_notes": null
    },
    {
      "id": "8f9a27e9-b1ed-40e4-bd26-ac2bbfa9e6f4",
      "pet_id": "1918dd1c-6b34-4037-9698-07fc1eb23477",
      "title": "Attachment Continuity attach-fix-20260212T130147Z #1",
      "description": "Loop 1",
      "location": "Amman",
      "priority": "high",
      "status": "completed",
      "requested_by": "199cd06e-0ac0-4ddc-beaa-2392c4195880",
      "requested_by_name": "Attach Fix User",
      "assigned_vet_id": "1382dcc7-3cd5-4be2-b4e9-8bad76a7d864",
      "assigned_clinic_id": null,
      "attachments": [
        "inline://attach-fix-20260212T130147Z-1-a",
        "inline://attach-fix-20260212T130147Z-1-b"
      ],
      "follow_up_context": "Loop-1",
      "follow_up_due_date": null,
      "reminder_enabled": false,
      "created_at": "2026-02-12T13:01:49.597000",
      "updated_at": "2026-02-12T13:01:49.617000",
      "diagnosis": "Dx-1",
      "prescription": "Rx-1",
      "vet_notes": null
    },
    {
      "id": "18ef11e2-0593-4b4c-bc97-29c60e48e0e9",
      "pet_id": "1918dd1c-6b34-4037-9698-07fc1eb23477",
      "title": "Attachment Continuity attach-fix-20260212T130147Z #0",
      "description": "Loop 0",
      "location": "Amman",
      "priority": "high",
      "status": "completed",
      "requested_by": "199cd06e-0ac0-4ddc-beaa-2392c4195880",
      "requested_by_name": "Attach Fix User",
      "assigned_vet_id": "1382dcc7-3cd5-4be2-b4e9-8bad76a7d864",
      "assigned_clinic_id": null,
      "attachments": [
        "inline://attach-fix-20260212T130147Z-0-a",
        "inline://attach-fix-20260212T130147Z-0-b"
      ],
      "follow_up_context": "Loop-0",
      "follow_up_due_date": null,
      "reminder_enabled": false,
      "created_at": "2026-02-12T13:01:49.564000",
      "updated_at": "2026-02-12T13:01:49.586000",
      "diagnosis": "Dx-0",
      "prescription": "Rx-0",
      "vet_notes": null
    },
    {
      "id": "888496de-31a2-4259-b357-dd619c9ab25a",
      "pet_id": "b854ca0c-bdcb-4a5b-acb2-72763ff5a72b",
      "title": "Attachment Continuity attach-fix-20260212T130126Z #11",
      "description": "Loop 11",
      "location": "Amman",
      "priority": "high",
      "status": "completed",
      "requested_by": "bc5617a8-1953-43e2-bba0-aec72d151720",
      "requested_by_name": "Attach Fix User",
      "assigned_vet_id": "1382dcc7-3cd5-4be2-b4e9-8bad76a7d864",
      "assigned_clinic_id": null,
      "attachments": [
        "inline://attach-fix-20260212T130126Z-11-a",
        "inline://attach-fix-20260212T130126Z-11-b"
      ],
      "follow_up_context": "Loop-11",
      "follow_up_due_date": null,
      "reminder_enabled": false,
      "created_at": "2026-02-12T13:01:28.558000",
      "updated_at": "2026-02-12T13:01:28.582000",
      "diagnosis": "Dx-11",
      "prescription": "Rx-11",
      "vet_notes": null
    },
    {
      "id": "2c8edac8-443b-4c69-9721-46110c3a2e4d",
      "pet_id": "b854ca0c-bdcb-4a5b-acb2-72763ff5a72b",
      "title": "Attachment Continuity attach-fix-20260212T130126Z #10",
      "description": "Loop 10",
      "location": "Amman",
      "priority": "high",
      "status": "completed",
      "requested_by": "bc5617a8-1953-43e2-bba0-aec72d151720",
      "requested_by_name": "Attach Fix User",
      "assigned_vet_id": "1382dcc7-3cd5-4be2-b4e9-8bad76a7d864",
      "assigned_clinic_id": null,
      "attachments": [
        "inline://attach-fix-20260212T130126Z-10-a",
        "inline://attach-fix-20260212T130126Z-10-b"
      ],
      "follow_up_context": "Loop-10",
      "follow_up_due_date": null,
      "reminder_enabled": false,
      "created_at": "2026-02-12T13:01:28.526000",
      "updated_at": "2026-02-12T13:01:28.548000",
      "diagnosis": "Dx-10",
      "prescription": "Rx-10",
      "vet_notes": null
    },
    {
      "id": "00bf9ec8-26c8-4ffa-b1d8-6f3cbdf71853",
      "pet_id": "b854ca0c-bdcb-4a5b-acb2-72763ff5a72b",
      "title": "Attachment Continuity attach-fix-20260212T130126Z #9",
      "description": "Loop 9",
      "location": "Amman",
      "priority": "high",
      "status": "completed",
      "requested_by": "bc5617a8-1953-43e2-bba0-aec72d151720",
      "requested_by_name": "Attach Fix User",
      "assigned_vet_id": "1382dcc7-3cd5-4be2-b4e9-8bad76a7d864",
      "assigned_clinic_id": null,
      "attachments": [
        "inline://attach-fix-20260212T130126Z-9-a",
        "inline://attach-fix-20260212T130126Z-9-b"
      ],
      "follow_up_context": "Loop-9",
      "follow_up_due_date": null,
      "reminder_enabled": false,
      "created_at": "2026-02-12T13:01:28.497000",
      "updated_at": "2026-02-12T13:01:28.518000",
      "diagnosis": "Dx-9",
      "prescription": "Rx-9",
      "vet_notes": null
    },
    {
      "id": "4a4175c2-bd2b-4df7-90a8-b0390b6ca91e",
      "pet_id": "b854ca0c-bdcb-4a5b-acb2-72763ff5a72b",
      "title": "Attachment Continuity attach-fix-20260212T130126Z #8",
      "description": "Loop 8",
      "location": "Amman",
      "priority": "high",
      "status": "completed",
      "requested_by": "bc5617a8-1953-43e2-bba0-aec72d151720",
      "requested_by_name": "Attach Fix User",
      "assigned_vet_id": "1382dcc7-3cd5-4be2-b4e9-8bad76a7d864",
      "assigned_clinic_id": null,
      "attachments": [
        "inline://attach-fix-20260212T130126Z-8-a",
        "inline://attach-fix-20260212T130126Z-8-b"
      ],
      "follow_up_context": "Loop-8",
      "follow_up_due_date": null,
      "reminder_enabled": false,
      "created_at": "2026-02-12T13:01:28.471000",
      "updated_at": "2026-02-12T13:01:28.489000",
      "diagnosis": "Dx-8",
      "prescription": "Rx-8",
      "vet_notes": null
    },
    {
      "id": "da4d8ed9-4479-4c18-9760-a61004ff557e",
      "pet_id": "b854ca0c-bdcb-4a5b-acb2-72763ff5a72b",
      "title": "Attachment Continuity attach-fix-20260212T130126Z #7",
      "description": "Loop 7",
      "location": "Amman",
      "priority": "high",
      "status": "completed",
      "requested_by": "bc5617a8-1953-43e2-bba0-aec72d151720",
      "requested_by_name": "Attach Fix User",
      "assigned_vet_id": "1382dcc7-3cd5-4be2-b4e9-8bad76a7d864",
      "assigned_clinic_id": null,
      "attachments": [
        "inline://attach-fix-20260212T130126Z-7-a",
        "inline://attach-fix-20260212T130126Z-7-b"
      ],
      "follow_up_context": "Loop-7",
      "follow_up_due_date": null,
      "reminder_enabled": false,
      "created_at": "2026-02-12T13:01:28.446000",
      "updated_at": "2026-02-12T13:01:28.463000",
      "diagnosis": "Dx-7",
      "prescription": "Rx-7",
      "vet_notes": null
    },
    {
      "id": "f26f2270-35ae-4a2a-9612-2c708e3608a9",
      "pet_id": "b854ca0c-bdcb-4a5b-acb2-72763ff5a72b",
      "title": "Attachment Continuity attach-fix-20260212T130126Z #6",
      "description": "Loop 6",
      "location": "Amman",
      "priority": "high",
      "status": "completed",
      "requested_by": "bc5617a8-1953-43e2-bba0-aec72d151720",
      "requested_by_name": "Attach Fix User",
      "assigned_vet_id": "1382dcc7-3cd5-4be2-b4e9-8bad76a7d864",
      "assigned_clinic_id": null,
      "attachments": [
        "inline://attach-fix-20260212T130126Z-6-a",
        "inline://attach-fix-20260212T130126Z-6-b"
      ],
      "follow_up_context": "Loop-6",
      "follow_up_due_date": null,
      "reminder_enabled": false,
      "created_at": "2026-02-12T13:01:28.418000",
      "updated_at": "2026-02-12T13:01:28.436000",
      "diagnosis": "Dx-6",
      "prescription": "Rx-6",
      "vet_notes": null
    },
    {
      "id": "e2e2a5cf-fe27-4601-88de-c871d6484d59",
      "pet_id": "b854ca0c-bdcb-4a5b-acb2-72763ff5a72b",
      "title": "Attachment Continuity attach-fix-20260212T130126Z #5",
      "description": "Loop 5",
      "location": "Amman",
      "priority": "high",
      "status": "completed",
      "requested_by": "bc5617a8-1953-43e2-bba0-aec72d151720",
      "requested_by_name": "Attach Fix User",
      "assigned_vet_id": "1382dcc7-3cd5-4be2-b4e9-8bad76a7d864",
      "assigned_clinic_id": null,
      "attachments": [
        "inline://attach-fix-20260212T130126Z-5-a",
        "inline://attach-fix-20260212T130126Z-5-b"
      ],
      "follow_up_context": "Loop-5",
      "follow_up_due_date": null,
      "reminder_enabled": false,
      "created_at": "2026-02-12T13:01:28.394000",
      "updated_at": "2026-02-12T13:01:28.410000",
      "diagnosis": "Dx-5",
      "prescription": "Rx-5",
      "vet_notes": null
    },
    {
      "id": "f46ec615-a6c0-4829-83b2-f988862fc40d",
      "pet_id": "b854ca0c-bdcb-4a5b-acb2-72763ff5a72b",
      "title": "Attachment Continuity attach-fix-20260212T130126Z #4",
      "description": "Loop 4",
      "location": "Amman",
      "priority": "high",
      "status": "completed",
      "requested_by": "bc5617a8-1953-43e2-bba0-aec72d151720",
      "requested_by_name": "Attach Fix User",
      "assigned_vet_id": "1382dcc7-3cd5-4be2-b4e9-8bad76a7d864",
      "assigned_clinic_id": null,
      "attachments": [
        "inline://attach-fix-20260212T130126Z-4-a",
        "inline://attach-fix-20260212T130126Z-4-b"
      ],
      "follow_up_context": "Loop-4",
      "follow_up_due_date": null,
      "reminder_enabled": false,
      "created_at": "2026-02-12T13:01:28.368000",
      "updated_at": "2026-02-12T13:01:28.385000",
      "diagnosis": "Dx-4",
      "prescription": "Rx-4",
      "vet_notes": null
    },
    {
      "id": "26752216-18c5-484c-8205-7e24e101153c",
      "pet_id": "b854ca0c-bdcb-4a5b-acb2-72763ff5a72b",
      "title": "Attachment Continuity attach-fix-20260212T130126Z #3",
      "description": "Loop 3",
      "location": "Amman",
      "priority": "high",
      "status": "completed",
      "requested_by": "bc5617a8-1953-43e2-bba0-aec72d151720",
      "requested_by_name": "Attach Fix User",
      "assigned_vet_id": "1382dcc7-3cd5-4be2-b4e9-8bad76a7d864",
      "assigned_clinic_id": null,
      "attachments": [
        "inline://attach-fix-20260212T130126Z-3-a",
        "inline://attach-fix-20260212T130126Z-3-b"
      ],
      "follow_up_context": "Loop-3",
      "follow_up_due_date": null,
      "reminder_enabled": false,
      "created_at": "2026-02-12T13:01:28.344000",
      "updated_at": "2026-02-12T13:01:28.360000",
      "diagnosis": "Dx-3",
      "prescription": "Rx-3",
      "vet_notes": null
    },
    {
      "id": "f5902707-203d-4e74-b6c8-64605d8c1691",
      "pet_id": "b854ca0c-bdcb-4a5b-acb2-72763ff5a72b",
      "title": "Attachment Continuity attach-fix-20260212T130126Z #2",
      "description": "Loop 2",
      "location": "Amman",
      "priority": "high",
      "status": "completed",
      "requested_by": "bc5617a8-1953-43e2-bba0-aec72d151720",
      "requested_by_name": "Attach Fix User",
      "assigned_vet_id": "1382dcc7-3cd5-4be2-b4e9-8bad76a7d864",
      "assigned_clinic_id": null,
      "attachments": [
        "inline://attach-fix-20260212T130126Z-2-a",
        "inline://attach-fix-20260212T130126Z-2-b"
      ],
      "follow_up_context": "Loop-2",
      "follow_up_due_date": null,
      "reminder_enabled": false,
      "created_at": "2026-02-12T13:01:28.318000",
      "updated_at": "2026-02-12T13:01:28.335000",
      "diagnosis": "Dx-2",
      "prescription": "Rx-2",
      "vet_notes": null
    },
    {
      "id": "b6b6015a-b5dd-4627-bd1c-275c750766ba",
      "pet_id": "b854ca0c-bdcb-4a5b-acb2-72763ff5a72b",
      "title": "Attachment Continuity attach-fix-20260212T130126Z #1",
      "description": "Loop 1",
      "location": "Amman",
      "priority": "high",
      "status": "completed",
      "requested_by": "bc5617a8-1953-43e2-bba0-aec72d151720",
      "requested_by_name": "Attach Fix User",
      "assigned_vet_id": "1382dcc7-3cd5-4be2-b4e9-8bad76a7d864",
      "assigned_clinic_id": null,
      "attachments": [
        "inline://attach-fix-20260212T130126Z-1-a",
        "inline://attach-fix-20260212T130126Z-1-b"
      ],
      "follow_up_context": "Loop-1",
      "follow_up_due_date": null,
      "reminder_enabled": false,
      "created_at": "2026-02-12T13:01:28.294000",
      "updated_at": "2026-02-12T13:01:28.311000",
      "diagnosis": "Dx-1",
      "prescription": "Rx-1",
      "vet_notes": null
    },
    {
      "id": "6b2acf5d-fc03-4e37-ab49-30caed5ebeae",
      "pet_id": "b854ca0c-bdcb-4a5b-acb2-72763ff5a72b",
      "title": "Attachment Continuity attach-fix-20260212T130126Z #0",
      "description": "Loop 0",
      "location": "Amman",
      "priority": "high",
      "status": "completed",
      "requested_by": "bc5617a8-1953-43e2-bba0-aec72d151720",
      "requested_by_name": "Attach Fix User",
      "assigned_vet_id": "1382dcc7-3cd5-4be2-b4e9-8bad76a7d864",
      "assigned_clinic_id": null,
      "attachments": [
        "inline://attach-fix-20260212T130126Z-0-a",
        "inline://attach-fix-20260212T130126Z-0-b"
      ],
      "follow_up_context": "Loop-0",
      "follow_up_due_date": null,
      "reminder_enabled": false,
      "created_at": "2026-02-12T13:01:28.260000",
      "updated_at": "2026-02-12T13:01:28.286000",
      "diagnosis": "Dx-0",
      "prescription": "Rx-0",
      "vet_notes": null
    },
    {
      "id": "598cf8e2-7875-4379-8685-ec411c22d5a4",
      "pet_id": "616b96bb-6d26-4001-9d50-82921db7c2c7",
      "title": "Follow-up review medical-gap-close-20260212T125032Z",
      "description": "Pet still coughing after meds.",
      "location": "Amman",
      "priority": "high",
      "status": "completed",
      "requested_by": "cd635635-5146-4845-a47a-b7f04893fe67",
      "requested_by_name": "Beta Med Gap",
      "assigned_vet_id": "1382dcc7-3cd5-4be2-b4e9-8bad76a7d864",
      "assigned_clinic_id": null,
      "attachments": [
        "data:image/jpeg;base64,ZmFrZS1hdHRhY2gtMQ==",
        "data:image/jpeg;base64,ZmFrZS1hdHRhY2gtMg=="
      ],
      "follow_up_context": "Symptoms improved for 2 days then returned.",
      "follow_up_due_date": "2026-02-19",
      "reminder_enabled": true,
      "created_at": "2026-02-12T12:50:33.834000",
      "updated_at": "2026-02-12T12:50:33.867000",
      "diagnosis": "Upper respiratory inflammation",
      "prescription": "Continue antibiotics 5 days",
      "vet_notes": "Hydration + steam"
    },
    {
      "id": "921cf7e8-fcdd-4b1b-872c-f25196807698",
      "pet_id": "ecc50b7f-2b81-4edb-8926-f1444c1f7052",
      "title": "Follow-up review medical-gap-close-20260212T124955Z",
      "description": "Pet still coughing after meds.",
      "location": "Amman",
      "priority": "high",
      "status": "completed",
      "requested_by": "41a9e141-75de-423e-a7ac-6b13efe61b09",
      "requested_by_name": "Beta Med Gap",
      "assigned_vet_id": "1382dcc7-3cd5-4be2-b4e9-8bad76a7d864",
      "assigned_clinic_id": null,
      "created_at": "2026-02-12T12:49:57.465000",
      "updated_at": "2026-02-12T12:49:57.492000",
      "diagnosis": "Upper respiratory inflammation",
      "prescription": "Continue antibiotics 5 days",
      "vet_notes": "Hydration + steam"
    },
    {
      "id": "faf235bf-7126-4334-afb2-aba0a1ed906d",
      "pet_id": "221cf038-a6b7-422d-9303-3d767fd32c88",
      "title": "Continuity visit 2 final-medical-beta-20260212T123719Z",
      "description": "Continuity symptoms #2",
      "location": "Amman",
      "priority": "normal",
      "status": "completed",
      "requested_by": "30c4a5aa-f7ad-49fb-9a41-8d8af873fc65",
      "requested_by_name": "Beta Final Medical",
      "assigned_vet_id": "1382dcc7-3cd5-4be2-b4e9-8bad76a7d864",
      "assigned_clinic_id": null,
      "created_at": "2026-02-12T12:37:25.542000",
      "updated_at": "2026-02-12T12:37:25.560000",
      "diagnosis": "Dx2",
      "prescription": "Rx2",
      "vet_notes": "Follow-up 2"
    },
    {
      "id": "ee9894ec-482b-4420-a92c-7545dc6227e1",
      "pet_id": "221cf038-a6b7-422d-9303-3d767fd32c88",
      "title": "Continuity visit 1 final-medical-beta-20260212T123719Z",
      "description": "Continuity symptoms #1",
      "location": "Amman",
      "priority": "normal",
      "status": "completed",
      "requested_by": "30c4a5aa-f7ad-49fb-9a41-8d8af873fc65",
      "requested_by_name": "Beta Final Medical",
      "assigned_vet_id": "1382dcc7-3cd5-4be2-b4e9-8bad76a7d864",
      "assigned_clinic_id": null,
      "created_at": "2026-02-12T12:37:25.507000",
      "updated_at": "2026-02-12T12:37:25.531000",
      "diagnosis": "Dx1",
      "prescription": "Rx1",
      "vet_notes": "Follow-up 1"
    },
    {
      "id": "6b4e14dd-e294-4553-b5a1-4e8737d62fd8",
      "pet_id": "dc441305-86f8-4405-9484-8ad973998f35",
      "title": "final-med-20260212T123634Z-attach-check",
      "description": "need tests",
      "location": null,
      "priority": "normal",
      "status": "in_progress",
      "requested_by": "97052c92-910f-4061-976f-c8a991cdaaf4",
      "requested_by_name": "Demo Clinic",
      "assigned_vet_id": "1382dcc7-3cd5-4be2-b4e9-8bad76a7d864",
      "assigned_clinic_id": null,
      "created_at": "2026-02-12T12:36:34.892000",
      "updated_at": "2026-02-12T12:36:34.899000"
    },
    {
      "id": "7fe66ca8-a6cd-4b6f-a831-5dd0fe9c7161",
      "pet_id": "d9986129-0f9f-4671-b145-21f395369df9",
      "title": "Continuity visit 2 final-medical-beta-20260212T123613Z",
      "description": "Continuity symptoms #2",
      "location": "Amman",
      "priority": "normal",
      "status": "completed",
      "requested_by": "c186ed9f-e1d8-4d07-967d-79fac2636d37",
      "requested_by_name": "Beta Final Medical",
      "assigned_vet_id": "1382dcc7-3cd5-4be2-b4e9-8bad76a7d864",
      "assigned_clinic_id": null,
      "created_at": "2026-02-12T12:36:16.604000",
      "updated_at": "2026-02-12T12:36:16.621000",
      "diagnosis": "Dx2",
      "prescription": "Rx2",
      "vet_notes": "Follow-up 2"
    },
    {
      "id": "8338ac43-0fa3-4a17-8c10-e471c3a1ca70",
      "pet_id": "d9986129-0f9f-4671-b145-21f395369df9",
      "title": "Continuity visit 1 final-medical-beta-20260212T123613Z",
      "description": "Continuity symptoms #1",
      "location": "Amman",
      "priority": "normal",
      "status": "completed",
      "requested_by": "c186ed9f-e1d8-4d07-967d-79fac2636d37",
      "requested_by_name": "Beta Final Medical",
      "assigned_vet_id": "1382dcc7-3cd5-4be2-b4e9-8bad76a7d864",
      "assigned_clinic_id": null,
      "created_at": "2026-02-12T12:36:16.579000",
      "updated_at": "2026-02-12T12:36:16.595000",
      "diagnosis": "Dx1",
      "prescription": "Rx1",
      "vet_notes": "Follow-up 1"
    },
    {
      "id": "1ab1b52e-5d18-40bc-841b-cc515af21e7d",
      "pet_id": "b1c97255-3efb-4073-bf42-30cf31f9dbd7",
      "title": "Continuity visit 2 final-medical-beta-20260212T123508Z",
      "description": "Continuity symptoms #2",
      "location": "Amman",
      "priority": "normal",
      "status": "completed",
      "requested_by": "b6067667-1c01-4570-a5dd-08ff2e00f261",
      "requested_by_name": "Beta Final Medical",
      "assigned_vet_id": "1382dcc7-3cd5-4be2-b4e9-8bad76a7d864",
      "assigned_clinic_id": null,
      "created_at": "2026-02-12T12:35:12.718000",
      "updated_at": "2026-02-12T12:35:12.735000",
      "diagnosis": "Dx2",
      "prescription": "Rx2",
      "vet_notes": "Follow-up 2"
    },
    {
      "id": "9d0b0cb3-b1e0-4b2c-a5a5-959cbc769e80",
      "pet_id": "b1c97255-3efb-4073-bf42-30cf31f9dbd7",
      "title": "Continuity visit 1 final-medical-beta-20260212T123508Z",
      "description": "Continuity symptoms #1",
      "location": "Amman",
      "priority": "normal",
      "status": "completed",
      "requested_by": "b6067667-1c01-4570-a5dd-08ff2e00f261",
      "requested_by_name": "Beta Final Medical",
      "assigned_vet_id": "1382dcc7-3cd5-4be2-b4e9-8bad76a7d864",
      "assigned_clinic_id": null,
      "created_at": "2026-02-12T12:35:12.689000",
      "updated_at": "2026-02-12T12:35:12.707000",
      "diagnosis": "Dx1",
      "prescription": "Rx1",
      "vet_notes": "Follow-up 1"
    },
    {
      "id": "a18e9911-7a94-4920-96c3-1413dc4274ad",
      "pet_id": "1ebda4ce-8258-4e75-a654-91ec9817d5bf",
      "title": "Continuity visit 2 final-medical-beta-20260212T123423Z",
      "description": "Continuity symptoms #2",
      "location": "Amman",
      "priority": "normal",
      "status": "completed",
      "requested_by": "10bb4191-3c83-47ba-81c2-9cbfc810f2c2",
      "requested_by_name": "Beta Final Medical",
      "assigned_vet_id": "1382dcc7-3cd5-4be2-b4e9-8bad76a7d864",
      "assigned_clinic_id": null,
      "created_at": "2026-02-12T12:34:26.927000",
      "updated_at": "2026-02-12T12:34:26.948000",
      "diagnosis": "Dx2",
      "prescription": "Rx2",
      "vet_notes": "Follow-up 2"
    },
    {
      "id": "00d72ead-bd30-4f17-9ef3-1de1eeaa61e2",
      "pet_id": "1ebda4ce-8258-4e75-a654-91ec9817d5bf",
      "title": "Continuity visit 1 final-medical-beta-20260212T123423Z",
      "description": "Continuity symptoms #1",
      "location": "Amman",
      "priority": "normal",
      "status": "completed",
      "requested_by": "10bb4191-3c83-47ba-81c2-9cbfc810f2c2",
      "requested_by_name": "Beta Final Medical",
      "assigned_vet_id": "1382dcc7-3cd5-4be2-b4e9-8bad76a7d864",
      "assigned_clinic_id": null,
      "created_at": "2026-02-12T12:34:26.883000",
      "updated_at": "2026-02-12T12:34:26.912000",
      "diagnosis": "Dx1",
      "prescription": "Rx1",
      "vet_notes": "Follow-up 1"
    },
    {
      "id": "21c3e205-6653-4ded-9af0-0132d0a4344f",
      "pet_id": "ee622311-41f3-4d1b-854d-8fa86688be23",
      "title": "Care request 3 beta-vet-flow-20260212T120139Z",
      "description": "Symptoms for Kiwi-20139Z (beta-vet-flow-20260212T120139Z)",
      "location": "Amman",
      "priority": "normal",
      "status": "completed",
      "requested_by": "8de895c8-8aaf-42ba-b87b-cd9ff8d1e7b8",
      "requested_by_name": "Beta Vet Flow User",
      "assigned_vet_id": "1382dcc7-3cd5-4be2-b4e9-8bad76a7d864",
      "assigned_clinic_id": null,
      "created_at": "2026-02-12T12:01:41.422000",
      "updated_at": "2026-02-12T12:01:41.442000",
      "diagnosis": "Dx-Kiwi-20139Z",
      "prescription": "Rx-Kiwi-20139Z",
      "vet_notes": "Follow-up after 3 days for Kiwi-20139Z (beta-vet-flow-20260212T120139Z)"
    },
    {
      "id": "376ada76-f43e-4943-b6e6-f4ea5989e577",
      "pet_id": "8b587bd9-2569-4921-b2a6-663c11fd6add",
      "title": "Care request 2 beta-vet-flow-20260212T120139Z",
      "description": "Symptoms for Luna-20139Z (beta-vet-flow-20260212T120139Z)",
      "location": "Amman",
      "priority": "normal",
      "status": "completed",
      "requested_by": "8de895c8-8aaf-42ba-b87b-cd9ff8d1e7b8",
      "requested_by_name": "Beta Vet Flow User",
      "assigned_vet_id": "1382dcc7-3cd5-4be2-b4e9-8bad76a7d864",
      "assigned_clinic_id": null,
      "created_at": "2026-02-12T12:01:41.383000",
      "updated_at": "2026-02-12T12:01:41.407000",
      "diagnosis": "Dx-Luna-20139Z",
      "prescription": "Rx-Luna-20139Z",
      "vet_notes": "Follow-up after 3 days for Luna-20139Z (beta-vet-flow-20260212T120139Z)"
    },
    {
      "id": "9771b7cf-f05c-433c-848a-02bb4912b0d4",
      "pet_id": "f4f86b97-8773-42ca-bda7-fbe3292c65af",
      "title": "Care request 1 beta-vet-flow-20260212T120139Z",
      "description": "Symptoms for Milo-20139Z (beta-vet-flow-20260212T120139Z)",
      "location": "Amman",
      "priority": "high",
      "status": "completed",
      "requested_by": "8de895c8-8aaf-42ba-b87b-cd9ff8d1e7b8",
      "requested_by_name": "Beta Vet Flow User",
      "assigned_vet_id": "1382dcc7-3cd5-4be2-b4e9-8bad76a7d864",
      "assigned_clinic_id": null,
      "created_at": "2026-02-12T12:01:41.336000",
      "updated_at": "2026-02-12T12:01:41.355000",
      "diagnosis": "Dx-Milo-20139Z",
      "prescription": "Rx-Milo-20139Z",
      "vet_notes": "Follow-up after 3 days for Milo-20139Z (beta-vet-flow-20260212T120139Z)"
    },
    {
      "id": "15bbf200-e4e7-4a02-93e4-f8959af8959c",
      "pet_id": "1cf7609d-3f7b-4f8f-a52d-edbe5647da3c",
      "title": "Care request 3 beta-vet-flow-20260212T120025Z",
      "description": "Symptoms for Kiwi-20025Z (beta-vet-flow-20260212T120025Z)",
      "location": "Amman",
      "priority": "normal",
      "status": "completed",
      "requested_by": "77b18f80-48a2-4e36-bdfe-0dd9a7bc8db6",
      "requested_by_name": "Beta Vet Flow User",
      "assigned_vet_id": "1382dcc7-3cd5-4be2-b4e9-8bad76a7d864",
      "assigned_clinic_id": null,
      "created_at": "2026-02-12T12:00:27.516000",
      "updated_at": "2026-02-12T12:00:27.534000",
      "diagnosis": "Dx-Kiwi-20025Z",
      "prescription": "Rx-Kiwi-20025Z",
      "vet_notes": "Follow-up after 3 days for Kiwi-20025Z (beta-vet-flow-20260212T120025Z)"
    },
    {
      "id": "8a545aae-0dab-4827-8eed-4fa2cf8ff768",
      "pet_id": "8937ac8b-73d4-4ebd-81ae-6a334cfbbb2c",
      "title": "Care request 2 beta-vet-flow-20260212T120025Z",
      "description": "Symptoms for Luna-20025Z (beta-vet-flow-20260212T120025Z)",
      "location": "Amman",
      "priority": "normal",
      "status": "completed",
      "requested_by": "77b18f80-48a2-4e36-bdfe-0dd9a7bc8db6",
      "requested_by_name": "Beta Vet Flow User",
      "assigned_vet_id": "1382dcc7-3cd5-4be2-b4e9-8bad76a7d864",
      "assigned_clinic_id": null,
      "created_at": "2026-02-12T12:00:27.485000",
      "updated_at": "2026-02-12T12:00:27.503000",
      "diagnosis": "Dx-Luna-20025Z",
      "prescription": "Rx-Luna-20025Z",
      "vet_notes": "Follow-up after 3 days for Luna-20025Z (beta-vet-flow-20260212T120025Z)"
    },
    {
      "id": "48184dde-8d1c-4d16-9b09-4c5355487ce9",
      "pet_id": "c3dd3c9c-b22c-4a9a-82f3-dfd3d2da5135",
      "title": "Care request 1 beta-vet-flow-20260212T120025Z",
      "description": "Symptoms for Milo-20025Z (beta-vet-flow-20260212T120025Z)",
      "location": "Amman",
      "priority": "high",
      "status": "completed",
      "requested_by": "77b18f80-48a2-4e36-bdfe-0dd9a7bc8db6",
      "requested_by_name": "Beta Vet Flow User",
      "assigned_vet_id": "1382dcc7-3cd5-4be2-b4e9-8bad76a7d864",
      "assigned_clinic_id": null,
      "created_at": "2026-02-12T12:00:27.454000",
      "updated_at": "2026-02-12T12:00:27.473000",
      "diagnosis": "Dx-Milo-20025Z",
      "prescription": "Rx-Milo-20025Z",
      "vet_notes": "Follow-up after 3 days for Milo-20025Z (beta-vet-flow-20260212T120025Z)"
    },
    {
      "id": "6c220166-a2ca-4c57-bb16-a8a6a1e76f70",
      "pet_id": "7f36f4cf-1f12-449b-8f1b-00e518458428",
      "title": "Care request 3 beta-vet-flow-20260212T120010Z",
      "description": "Symptoms for Kiwi-20010Z (beta-vet-flow-20260212T120010Z)",
      "location": "Amman",
      "priority": "normal",
      "status": "completed",
      "requested_by": "9c8620f9-b840-48d6-9161-cc288c0f2602",
      "requested_by_name": "Beta Vet Flow User",
      "assigned_vet_id": "1382dcc7-3cd5-4be2-b4e9-8bad76a7d864",
      "assigned_clinic_id": null,
      "created_at": "2026-02-12T12:00:12.417000",
      "updated_at": "2026-02-12T12:00:12.442000",
      "diagnosis": "Dx-Kiwi-20010Z",
      "prescription": "Rx-Kiwi-20010Z",
      "vet_notes": "Follow-up after 3 days for Kiwi-20010Z (beta-vet-flow-20260212T120010Z)"
    },
    {
      "id": "acb8449e-198a-4d2d-b0fc-2301a17fa89c",
      "pet_id": "e7886c16-e943-455b-a297-cfef29c142b7",
      "title": "Care request 2 beta-vet-flow-20260212T120010Z",
      "description": "Symptoms for Luna-20010Z (beta-vet-flow-20260212T120010Z)",
      "location": "Amman",
      "priority": "normal",
      "status": "completed",
      "requested_by": "9c8620f9-b840-48d6-9161-cc288c0f2602",
      "requested_by_name": "Beta Vet Flow User",
      "assigned_vet_id": "1382dcc7-3cd5-4be2-b4e9-8bad76a7d864",
      "assigned_clinic_id": null,
      "created_at": "2026-02-12T12:00:12.378000",
      "updated_at": "2026-02-12T12:00:12.401000",
      "diagnosis": "Dx-Luna-20010Z",
      "prescription": "Rx-Luna-20010Z",
      "vet_notes": "Follow-up after 3 days for Luna-20010Z (beta-vet-flow-20260212T120010Z)"
    },
    {
      "id": "e74ca421-7792-4f95-826f-5f40af01c6f3",
      "pet_id": "1bd95558-63eb-4ab8-a845-d0081b078990",
      "title": "Care request 1 beta-vet-flow-20260212T120010Z",
      "description": "Symptoms for Milo-20010Z (beta-vet-flow-20260212T120010Z)",
      "location": "Amman",
      "priority": "high",
      "status": "completed",
      "requested_by": "9c8620f9-b840-48d6-9161-cc288c0f2602",
      "requested_by_name": "Beta Vet Flow User",
      "assigned_vet_id": "1382dcc7-3cd5-4be2-b4e9-8bad76a7d864",
      "assigned_clinic_id": null,
      "created_at": "2026-02-12T12:00:12.345000",
      "updated_at": "2026-02-12T12:00:12.363000",
      "diagnosis": "Dx-Milo-20010Z",
      "prescription": "Rx-Milo-20010Z",
      "vet_notes": "Follow-up after 3 days for Milo-20010Z (beta-vet-flow-20260212T120010Z)"
    },
    {
      "id": "1d44817b-39ee-4504-9d65-2bf867f328db",
      "pet_id": "3d138dfd-7839-4d1d-8d71-db79bd662d88",
      "title": "Follow-up case vet-alpha-20260212T115922Z",
      "description": "Limping after play, needs assessment",
      "location": "Amman",
      "priority": "high",
      "status": "completed",
      "requested_by": "97052c92-910f-4061-976f-c8a991cdaaf4",
      "requested_by_name": "Demo Clinic",
      "assigned_vet_id": "1382dcc7-3cd5-4be2-b4e9-8bad76a7d864",
      "assigned_clinic_id": null,
      "created_at": "2026-02-12T11:59:23.458000",
      "updated_at": "2026-02-12T11:59:23.486000",
      "diagnosis": "Mild soft-tissue strain in front right leg",
      "prescription": "Rest 5 days, meloxicam low dose once daily x3 days",
      "vet_notes": "No fracture signs. Recheck if limping persists >7 days."
    },
    {
      "id": "6dc00315-8752-4f93-a16b-16be008b3edc",
      "pet_id": "e265a381-0674-45c2-b4ea-ca0f99456b88",
      "title": "Negative Matrix Care",
      "description": "for role checks",
      "location": null,
      "priority": "normal",
      "status": "assigned",
      "requested_by": "e974e25f-3afb-4474-832c-b76635d6c242",
      "requested_by_name": "qa.user",
      "assigned_vet_id": null,
      "assigned_clinic_id": "2f1ccc94-a7ca-43dc-a5f8-4b36685de82a",
      "created_at": "2026-02-11T06:25:40.556000",
      "updated_at": "2026-02-11T06:25:40.721000"
    },
    {
      "id": "55bb1dcc-160e-475b-8ef2-d498db4f7aed",
      "pet_id": "4140bd89-9871-4cc5-8e1c-c2391a02bc03",
      "title": "Negative Matrix Care",
      "description": "for role checks",
      "location": null,
      "priority": "normal",
      "status": "assigned",
      "requested_by": "e974e25f-3afb-4474-832c-b76635d6c242",
      "requested_by_name": "qa.user",
      "assigned_vet_id": null,
      "assigned_clinic_id": "2f1ccc94-a7ca-43dc-a5f8-4b36685de82a",
      "created_at": "2026-02-11T06:25:30.352000",
      "updated_at": "2026-02-11T06:25:30.522000"
    },
    {
      "id": "92968467-be94-4acf-b7bd-27bfb90a01eb",
      "pet_id": "0f9a0969-c393-4abb-9c86-d251dbf72ca8",
      "title": "QA checkup",
      "description": "Regression test care request",
      "location": null,
      "priority": "normal",
      "status": "completed",
      "requested_by": "e974e25f-3afb-4474-832c-b76635d6c242",
      "requested_by_name": "qa.user",
      "assigned_vet_id": null,
      "assigned_clinic_id": null,
      "created_at": "2026-02-11T06:23:23.641000",
      "updated_at": "2026-02-11T06:23:23.699000"
    }
  ]
}